{
    "bibleVersion":  "KJV",
     "bibleLanguage":  "English",
     "fullBibleName":  "King James Version (1769)",
     "description":  "The King James Version, also known as the Authorized Version (AV) or the King James Bible (KJB), is an English translation of the Christian Bible, supported by King James I for the Church of England, begun in 1604 and completed in 1611. The translation is based on Textus Receptus (for NT) and Masoretic Text (for OT). This is the standard text of 1769 extensively re-edited by Benjamin Blayney at Oxford.",
     "scriptureSection":  "Old Testament",
     "internetAddress":  "https://www.kingjamesbibleonline.org/",
     "copyright":  "Public Domain",
     "bibleTextSource":  "Internet",
     "bookName":  "Joshua",
     "bookAbbreviation":  "Jos",
     "chapterNumber":  13,
     "verses":  [
        {
            "reference":  "Joshua 13:1",
             "verseNumber":  1,
             "scripture":  "Now Joshua was old and stricken in years; and the LORD said unto him, You are old and stricken in years, and there remains yet very much land to be possessed."
        },
        {
            "reference":  "Joshua 13:2",
             "verseNumber":  2,
             "scripture":  "This is the land that yet remains: all the borders of the Philistines, and all Geshuri,"
        },
        {
            "reference":  "Joshua 13:3",
             "verseNumber":  3,
             "scripture":  "From Sihor, which is before Egypt, even unto the borders of Ekron northward, which is counted to the Canaanite: five lords of the Philistines; the Gazathites, and the Ashdothites, the Eshkalonites, the Gittites, and the Ekronites; also the Avites:"
        },
        {
            "reference":  "Joshua 13:4",
             "verseNumber":  4,
             "scripture":  "From the south, all the land of the Canaanites, and Mearah that is beside the Sidonians unto Aphek, to the borders of the Amorites:"
        },
        {
            "reference":  "Joshua 13:5",
             "verseNumber":  5,
             "scripture":  "And the land of the Giblites, and all Lebanon, toward the sunrising, from Baalgad under mount Hermon unto the entering into Hamath."
        },
        {
            "reference":  "Joshua 13:6",
             "verseNumber":  6,
             "scripture":  "All the inhabitants of the hill country from Lebanon unto Misrephothmaim, and all the Sidonians, them will I drive out from before the children of Israel: only divide you it by lot unto the Israelites for an inheritance, as I have commanded you."
        },
        {
            "reference":  "Joshua 13:7",
             "verseNumber":  7,
             "scripture":  "Now therefore divide this land for an inheritance unto the nine tribes, and the half tribe of Manasseh,"
        },
        {
            "reference":  "Joshua 13:8",
             "verseNumber":  8,
             "scripture":  "With whom the Reubenites and the Gadites have received their inheritance, which Moses gave them, beyond Jordan eastward, even as Moses the servant of the LORD gave them;"
        },
        {
            "reference":  "Joshua 13:9",
             "verseNumber":  9,
             "scripture":  "From Aroer, that is upon the bank of the river Arnon, and the city that is in the midst of the river, and all the plain of Medeba unto Dibon;"
        },
        {
            "reference":  "Joshua 13:10",
             "verseNumber":  10,
             "scripture":  "And all the cities of Sihon king of the Amorites, which reigned in Heshbon, unto the border of the children of Ammon;"
        },
        {
            "reference":  "Joshua 13:11",
             "verseNumber":  11,
             "scripture":  "And Gilead, and the border of the Geshurites and Maachathites, and all mount Hermon, and all Bashan unto Salcah;"
        },
        {
            "reference":  "Joshua 13:12",
             "verseNumber":  12,
             "scripture":  "All the kingdom of Og in Bashan, which reigned in Ashtaroth and in Edrei, who remained of the remnant of the giants: for these did Moses strike, and cast them out."
        },
        {
            "reference":  "Joshua 13:13",
             "verseNumber":  13,
             "scripture":  "Nevertheless the children of Israel expelled not the Geshurites, nor the Maachathites: but the Geshurites and the Maachathites dwell among the Israelites until this day."
        },
        {
            "reference":  "Joshua 13:14",
             "verseNumber":  14,
             "scripture":  "Only unto the tribes of Levi he gave none inheritance; the sacrifices of the LORD God of Israel made by fire are their inheritance, as he said unto them."
        },
        {
            "reference":  "Joshua 13:15",
             "verseNumber":  15,
             "scripture":  "And Moses gave unto the tribe of the children of Reuben inheritance according to their families."
        },
        {
            "reference":  "Joshua 13:16",
             "verseNumber":  16,
             "scripture":  "And their coast was from Aroer, that is on the bank of the river Arnon, and the city that is in the midst of the river, and all the plain by Medeba;"
        },
        {
            "reference":  "Joshua 13:17",
             "verseNumber":  17,
             "scripture":  "Heshbon, and all her cities that are in the plain; Dibon, and Bamothbaal, and Bethbaalmeon,"
        },
        {
            "reference":  "Joshua 13:18",
             "verseNumber":  18,
             "scripture":  "And Jahaza, and Kedemoth, and Mephaath,"
        },
        {
            "reference":  "Joshua 13:19",
             "verseNumber":  19,
             "scripture":  "And Kirjathaim, and Sibmah, and Zarethshahar in the mount of the valley,"
        },
        {
            "reference":  "Joshua 13:20",
             "verseNumber":  20,
             "scripture":  "And Bethpeor, and Ashdothpisgah, and Bethjeshimoth,"
        },
        {
            "reference":  "Joshua 13:21",
             "verseNumber":  21,
             "scripture":  "And all the cities of the plain, and all the kingdom of Sihon king of the Amorites, which reigned in Heshbon, whom Moses stroke with the princes of Midian, Evi, and Rekem, and Zur, and Hur, and Reba, which were dukes of Sihon, dwelling in the country."
        },
        {
            "reference":  "Joshua 13:22",
             "verseNumber":  22,
             "scripture":  "Balaam also the son of Beor, the fortune teller, did the children of Israel slay with the sword among them that were slain by them."
        },
        {
            "reference":  "Joshua 13:23",
             "verseNumber":  23,
             "scripture":  "And the border of the children of Reuben was Jordan, and the border thereof. This was the inheritance of the children of Reuben after their families, the cities and the villages thereof."
        },
        {
            "reference":  "Joshua 13:24",
             "verseNumber":  24,
             "scripture":  "And Moses gave inheritance unto the tribe of Gad, even unto the children of Gad according to their families."
        },
        {
            "reference":  "Joshua 13:25",
             "verseNumber":  25,
             "scripture":  "And their coast was Jazer, and all the cities of Gilead, and half the land of the children of Ammon, unto Aroer that is before Rabbah;"
        },
        {
            "reference":  "Joshua 13:26",
             "verseNumber":  26,
             "scripture":  "And from Heshbon unto Ramathmizpeh, and Betonim; and from Mahanaim unto the border of Debir;"
        },
        {
            "reference":  "Joshua 13:27",
             "verseNumber":  27,
             "scripture":  "And in the valley, Betharam, and Bethnimrah, and Succoth, and Zaphon, the rest of the kingdom of Sihon king of Heshbon, Jordan and his border, even unto the edge of the sea of Chinnereth on the other side Jordan eastward."
        },
        {
            "reference":  "Joshua 13:28",
             "verseNumber":  28,
             "scripture":  "This is the inheritance of the children of Gad after their families, the cities, and their villages."
        },
        {
            "reference":  "Joshua 13:29",
             "verseNumber":  29,
             "scripture":  "And Moses gave inheritance unto the half tribe of Manasseh: and this was the possession of the half tribe of the children of Manasseh by their families."
        },
        {
            "reference":  "Joshua 13:30",
             "verseNumber":  30,
             "scripture":  "And their coast was from Mahanaim, all Bashan, all the kingdom of Og king of Bashan, and all the towns of Jair, which are in Bashan, threescore cities:"
        },
        {
            "reference":  "Joshua 13:31",
             "verseNumber":  31,
             "scripture":  "And half Gilead, and Ashtaroth, and Edrei, cities of the kingdom of Og in Bashan, were pertaining unto the children of Machir the son of Manasseh, even to the one half of the children of Machir by their families."
        },
        {
            "reference":  "Joshua 13:32",
             "verseNumber":  32,
             "scripture":  "These are the countries which Moses did distribute for inheritance in the plains of Moab, on the other side Jordan, by Jericho, eastward."
        },
        {
            "reference":  "Joshua 13:33",
             "verseNumber":  33,
             "scripture":  "But unto the tribe of Levi Moses gave not any inheritance: the LORD God of Israel was their inheritance, as he said unto them."
        }
    ]
}